{
    "# life regenerated per second": {
        "gen": "# life regenerated per second",
        "org": [],
        "params": [
            {
                "pos": 0,
                "type": "R",
                "value": ""
            }
        ]
    },
    "# to all attributes": {
        "gen": "# to all attributes",
        "org": [],
        "params": [
            {
                "pos": 0,
                "type": "R",
                "value": ""
            }
        ]
    },
    "# to armour": {
        "gen": "# to armour",
        "org": [],
        "params": [
            {
                "pos": 0,
                "type": "R",
                "value": ""
            }
        ]
    },
    "# to armour or evasion rating": {
        "gen": "# to armour or evasion rating",
        "org": [],
        "params": [
            {
                "pos": 0,
                "type": "R",
                "value": ""
            }
        ]
    },
    "# to dexterity": {
        "gen": "# to dexterity",
        "org": [],
        "params": [
            {
                "pos": 0,
                "type": "R",
                "value": ""
            }
        ]
    },
    "# to evasion rating": {
        "gen": "# to evasion rating",
        "org": [],
        "params": [
            {
                "pos": 0,
                "type": "R",
                "value": ""
            }
        ]
    },
    "# to intelligence": {
        "gen": "# to intelligence",
        "org": [],
        "params": [
            {
                "pos": 0,
                "type": "R",
                "value": ""
            }
        ]
    },
    "# to level of socketed chaos gems": {
        "gen": "# to level of socketed chaos gems",
        "org": [],
        "params": [
            {
                "pos": 0,
                "type": "R",
                "value": ""
            }
        ]
    },
    "# to level of socketed cold gems": {
        "gen": "# to level of socketed cold gems",
        "org": [],
        "params": [
            {
                "pos": 0,
                "type": "R",
                "value": ""
            }
        ]
    },
    "# to level of socketed fire gems": {
        "gen": "# to level of socketed fire gems",
        "org": [],
        "params": [
            {
                "pos": 0,
                "type": "R",
                "value": ""
            }
        ]
    },
    "# to level of socketed intelligence gems": {
        "gen": "# to level of socketed intelligence gems",
        "org": [],
        "params": [
            {
                "pos": 0,
                "type": "R",
                "value": ""
            }
        ]
    },
    "# to level of socketed lightning gems": {
        "gen": "# to level of socketed lightning gems",
        "org": [],
        "params": [
            {
                "pos": 0,
                "type": "R",
                "value": ""
            }
        ]
    },
    "# to level of socketed minion gems": {
        "gen": "# to level of socketed minion gems",
        "org": [],
        "params": [
            {
                "pos": 0,
                "type": "R",
                "value": ""
            }
        ]
    },
    "# to level of socketed strength gems": {
        "gen": "# to level of socketed strength gems",
        "org": [],
        "params": [
            {
                "pos": 0,
                "type": "R",
                "value": ""
            }
        ]
    },
    "# to maximum energy shield": {
        "gen": "# to maximum energy shield",
        "org": [],
        "params": [
            {
                "pos": 0,
                "type": "R",
                "value": ""
            }
        ]
    },
    "# to maximum life": {
        "gen": "# to maximum life",
        "org": [],
        "params": [
            {
                "pos": 0,
                "type": "R",
                "value": ""
            }
        ]
    },
    "# to maximum mana": {
        "gen": "# to maximum mana",
        "org": [],
        "params": [
            {
                "pos": 0,
                "type": "R",
                "value": ""
            }
        ]
    },
    "# to maximum number of spectres": {
        "gen": "# to maximum number of spectres",
        "org": [],
        "params": [
            {
                "pos": 0,
                "type": "R",
                "value": ""
            }
        ]
    },
    "# to strength": {
        "gen": "# to strength",
        "org": [],
        "params": [
            {
                "pos": 0,
                "type": "R",
                "value": ""
            }
        ]
    },
    "#% additional physical damage reduction while moving": {
        "gen": "#% additional physical damage reduction while moving",
        "org": [],
        "params": [
            {
                "pos": 0,
                "type": "R",
                "value": ""
            }
        ]
    },
    "#% chance to avoid being frozen": {
        "gen": "#% chance to avoid being frozen",
        "org": [],
        "params": [
            {
                "pos": 0,
                "type": "R",
                "value": ""
            }
        ]
    },
    "#% chance to avoid being ignited": {
        "gen": "#% chance to avoid being ignited",
        "org": [],
        "params": [
            {
                "pos": 0,
                "type": "R",
                "value": ""
            }
        ]
    },
    "#% chance to avoid being knocked back": {
        "gen": "#% chance to avoid being knocked back",
        "org": [],
        "params": [
            {
                "pos": 0,
                "type": "R",
                "value": ""
            }
        ]
    },
    "#% chance to avoid being poisoned": {
        "gen": "#% chance to avoid being poisoned",
        "org": [],
        "params": [
            {
                "pos": 0,
                "type": "R",
                "value": ""
            }
        ]
    },
    "#% chance to avoid being shocked": {
        "gen": "#% chance to avoid being shocked",
        "org": [],
        "params": [
            {
                "pos": 0,
                "type": "R",
                "value": ""
            }
        ]
    },
    "#% chance to avoid being stunned": {
        "gen": "#% chance to avoid being stunned",
        "org": [],
        "params": [
            {
                "pos": 0,
                "type": "R",
                "value": ""
            }
        ]
    },
    "#% chance to avoid bleeding": {
        "gen": "#% chance to avoid bleeding",
        "org": [],
        "params": [
            {
                "pos": 0,
                "type": "R",
                "value": ""
            }
        ]
    },
    "#% chance to avoid elemental ailments": {
        "gen": "#% chance to avoid elemental ailments",
        "org": [],
        "params": [
            {
                "pos": 0,
                "type": "R",
                "value": ""
            }
        ]
    },
    "#% chance to avoid projectile": {
        "gen": "#% chance to avoid projectile",
        "org": [],
        "params": [
            {
                "pos": 0,
                "type": "R",
                "value": ""
            }
        ]
    },
    "#% chance to avoid projectiles": {
        "gen": "#% chance to avoid projectiles",
        "org": [],
        "params": [
            {
                "pos": 0,
                "type": "R",
                "value": ""
            }
        ]
    },
    "#% chance to dodge attack hits": {
        "gen": "#% chance to dodge attack hits",
        "org": [],
        "params": [
            {
                "pos": 0,
                "type": "R",
                "value": ""
            }
        ]
    },
    "#% chance to dodge attacks": {
        "gen": "#% chance to dodge attacks",
        "org": [],
        "params": [
            {
                "pos": 0,
                "type": "R",
                "value": ""
            }
        ]
    },
    "#% chance to dodge spell damage": {
        "gen": "#% chance to dodge spell damage",
        "org": [],
        "params": [
            {
                "pos": 0,
                "type": "R",
                "value": ""
            }
        ]
    },
    "#% chance to dodge spell hits": {
        "gen": "#% chance to dodge spell hits",
        "org": [],
        "params": [
            {
                "pos": 0,
                "type": "R",
                "value": ""
            }
        ]
    },
    "#% chance to gain an additional vaal soul on kill": {
        "gen": "#% chance to gain an additional vaal soul on kill",
        "org": [],
        "params": [
            {
                "pos": 0,
                "type": "R",
                "value": ""
            }
        ]
    },
    "#% chance to gain an endurance charge on kill": {
        "gen": "#% chance to gain an endurance charge on kill",
        "org": [],
        "params": [
            {
                "pos": 0,
                "type": "R",
                "value": ""
            }
        ]
    },
    "#% increased armour": {
        "gen": "#% increased armour",
        "org": [],
        "params": [
            {
                "pos": 0,
                "type": "R",
                "value": ""
            }
        ]
    },
    "#% increased armour and energy shield": {
        "gen": "#% increased armour and energy shield",
        "org": [],
        "params": [
            {
                "pos": 0,
                "type": "R",
                "value": ""
            }
        ]
    },
    "#% increased armour and evasion": {
        "gen": "#% increased armour and evasion",
        "org": [],
        "params": [
            {
                "pos": 0,
                "type": "R",
                "value": ""
            }
        ]
    },
    "#% increased armour and evasion rating": {
        "gen": "#% increased armour and evasion rating",
        "org": [],
        "params": [
            {
                "pos": 0,
                "type": "R",
                "value": ""
            }
        ]
    },
    "#% increased cooldown recovery speed": {
        "gen": "#% increased cooldown recovery speed",
        "org": [],
        "params": [
            {
                "pos": 0,
                "type": "R",
                "value": ""
            }
        ]
    },
    "#% increased elemental damage with attack skills": {
        "gen": "#% increased elemental damage with attack skills",
        "org": [],
        "params": [
            {
                "pos": 0,
                "type": "R",
                "value": ""
            }
        ]
    },
    "#% increased energy shield": {
        "gen": "#% increased energy shield",
        "org": [],
        "params": [
            {
                "pos": 0,
                "type": "R",
                "value": ""
            }
        ]
    },
    "#% increased evasion": {
        "gen": "#% increased evasion",
        "org": [],
        "params": [
            {
                "pos": 0,
                "type": "R",
                "value": ""
            }
        ]
    },
    "#% increased evasion and energy shield": {
        "gen": "#% increased evasion and energy shield",
        "org": [],
        "params": [
            {
                "pos": 0,
                "type": "R",
                "value": ""
            }
        ]
    },
    "#% increased evasion rating": {
        "gen": "#% increased evasion rating",
        "org": [],
        "params": [
            {
                "pos": 0,
                "type": "R",
                "value": ""
            }
        ]
    },
    "#% increased evasion rating and energy shield": {
        "gen": "#% increased evasion rating and energy shield",
        "org": [],
        "params": [
            {
                "pos": 0,
                "type": "R",
                "value": ""
            }
        ]
    },
    "#% increased mana regeneration rate": {
        "gen": "#% increased mana regeneration rate",
        "org": [],
        "params": [
            {
                "pos": 0,
                "type": "R",
                "value": ""
            }
        ]
    },
    "#% increased mana regeneration rate while moving": {
        "gen": "#% increased mana regeneration rate while moving",
        "org": [],
        "params": [
            {
                "pos": 0,
                "type": "R",
                "value": ""
            }
        ]
    },
    "#% increased maximum life": {
        "gen": "#% increased maximum life",
        "org": [],
        "params": [
            {
                "pos": 0,
                "type": "R",
                "value": ""
            }
        ]
    },
    "#% increased maximum mana": {
        "gen": "#% increased maximum mana",
        "org": [],
        "params": [
            {
                "pos": 0,
                "type": "R",
                "value": ""
            }
        ]
    },
    "#% increased movement speed": {
        "gen": "#% increased movement speed",
        "org": [],
        "params": [
            {
                "pos": 0,
                "type": "R",
                "value": ""
            }
        ]
    },
    "#% increased movement speed if you haven't been hit recently": {
        "gen": "#% increased movement speed if you haven't been hit recently",
        "org": [],
        "params": [
            {
                "pos": 0,
                "type": "R",
                "value": ""
            }
        ]
    },
    "#% increased movement speed if you've hit an enemy recently": {
        "gen": "#% increased movement speed if you've hit an enemy recently",
        "org": [],
        "params": [
            {
                "pos": 0,
                "type": "R",
                "value": ""
            }
        ]
    },
    "#% increased movement speed while on burning, chilled or shocked ground": {
        "gen": "#% increased movement speed while on burning, chilled or shocked ground",
        "org": [],
        "params": [
            {
                "pos": 0,
                "type": "R",
                "value": ""
            }
        ]
    },
    "#% increased rarity of items found": {
        "gen": "#% increased rarity of items found",
        "org": [],
        "params": [
            {
                "pos": 0,
                "type": "R",
                "value": ""
            }
        ]
    },
    "#% increased skill effect duration": {
        "gen": "#% increased skill effect duration",
        "org": [],
        "params": [
            {
                "pos": 0,
                "type": "R",
                "value": ""
            }
        ]
    },
    "#% increased stun and block recovery": {
        "gen": "#% increased stun and block recovery",
        "org": [],
        "params": [
            {
                "pos": 0,
                "type": "R",
                "value": ""
            }
        ]
    },
    "#% increased totem damage": {
        "gen": "#% increased totem damage",
        "org": [],
        "params": [
            {
                "pos": 0,
                "type": "R",
                "value": ""
            }
        ]
    },
    "#% increased totem placement speed": {
        "gen": "#% increased totem placement speed",
        "org": [],
        "params": [
            {
                "pos": 0,
                "type": "R",
                "value": ""
            }
        ]
    },
    "#% of damage taken gained as mana over # seconds when hit": {
        "gen": "#% of damage taken gained as mana over # seconds when hit",
        "org": [],
        "params": [
            {
                "pos": 0,
                "type": "R",
                "value": ""
            }
        ]
    },
    "#% of life regenerated per second": {
        "gen": "#% of life regenerated per second",
        "org": [],
        "params": [
            {
                "pos": 0,
                "type": "R",
                "value": ""
            }
        ]
    },
    "#% reduced attribute requirements": {
        "gen": "#% reduced attribute requirements",
        "org": [],
        "params": [
            {
                "pos": 0,
                "type": "R",
                "value": ""
            }
        ]
    },
    "#% reduced elemental ailment duration on you": {
        "gen": "#% reduced elemental ailment duration on you",
        "org": [],
        "params": [
            {
                "pos": 0,
                "type": "R",
                "value": ""
            }
        ]
    },
    "#% reduced elemental damage taken while not moving": {
        "gen": "#% reduced elemental damage taken while not moving",
        "org": [],
        "params": [
            {
                "pos": 0,
                "type": "R",
                "value": ""
            }
        ]
    },
    "#% reduced elemental damage taken while stationary": {
        "gen": "#% reduced elemental damage taken while stationary",
        "org": [],
        "params": [
            {
                "pos": 0,
                "type": "R",
                "value": ""
            }
        ]
    },
    "#% to chaos resistance": {
        "gen": "#% to chaos resistance",
        "org": [],
        "params": [
            {
                "pos": 0,
                "type": "R",
                "value": ""
            }
        ]
    },
    "#% to cold and lightning resistances": {
        "gen": "#% to cold and lightning resistances",
        "org": [],
        "params": [
            {
                "pos": 0,
                "type": "R",
                "value": ""
            }
        ]
    },
    "#% to cold resistance": {
        "gen": "#% to cold resistance",
        "org": [],
        "params": [
            {
                "pos": 0,
                "type": "R",
                "value": ""
            }
        ]
    },
    "#% to fire and cold resistances": {
        "gen": "#% to fire and cold resistances",
        "org": [],
        "params": [
            {
                "pos": 0,
                "type": "R",
                "value": ""
            }
        ]
    },
    "#% to fire and lightning resistances": {
        "gen": "#% to fire and lightning resistances",
        "org": [],
        "params": [
            {
                "pos": 0,
                "type": "R",
                "value": ""
            }
        ]
    },
    "#% to fire resistance": {
        "gen": "#% to fire resistance",
        "org": [],
        "params": [
            {
                "pos": 0,
                "type": "R",
                "value": ""
            }
        ]
    },
    "#% to lightning resistance": {
        "gen": "#% to lightning resistance",
        "org": [],
        "params": [
            {
                "pos": 0,
                "type": "R",
                "value": ""
            }
        ]
    },
    "can have multiple crafted mods": {
        "gen": "can have multiple crafted mods",
        "org": "can have multiple crafted mods",
        "params": []
    },
    "cannot be frozen": {
        "gen": "cannot be frozen",
        "org": "cannot be frozen",
        "params": []
    },
    "cannot be poisoned": {
        "gen": "cannot be poisoned",
        "org": "cannot be poisoned",
        "params": []
    },
    "cannot roll attack mods": {
        "gen": "cannot roll attack mods",
        "org": "cannot roll attack mods",
        "params": []
    },
    "cannot roll caster mods": {
        "gen": "cannot roll caster mods",
        "org": "cannot roll caster mods",
        "params": []
    },
    "cannot roll mods with required lvl above lvl #": {
        "gen": "cannot roll mods with required lvl above lvl #",
        "org": [],
        "params": [
            {
                "pos": 0,
                "type": "R",
                "value": ""
            }
        ]
    },
    "drops burning ground while moving, dealing # fire damage per second": {
        "gen": "drops burning ground while moving, dealing # fire damage per second",
        "org": [],
        "params": [
            {
                "pos": 0,
                "type": "R",
                "value": ""
            }
        ]
    },
    "grants level # aspect of the avian skill": {
        "gen": "grants level # aspect of the avian skill",
        "org": [],
        "params": [
            {
                "pos": 0,
                "type": "R",
                "value": ""
            }
        ]
    },
    "grants level # aspect of the cat skill": {
        "gen": "grants level # aspect of the cat skill",
        "org": [],
        "params": [
            {
                "pos": 0,
                "type": "R",
                "value": ""
            }
        ]
    },
    "grants level # aspect of the crab skill": {
        "gen": "grants level # aspect of the crab skill",
        "org": [],
        "params": [
            {
                "pos": 0,
                "type": "R",
                "value": ""
            }
        ]
    },
    "grants level # aspect of the spider skill": {
        "gen": "grants level # aspect of the spider skill",
        "org": [],
        "params": [
            {
                "pos": 0,
                "type": "R",
                "value": ""
            }
        ]
    },
    "grants level # decoy totem skill": {
        "gen": "grants level # decoy totem skill",
        "org": [],
        "params": [
            {
                "pos": 0,
                "type": "R",
                "value": ""
            }
        ]
    },
    "has # abyssal socket": {
        "gen": "has # abyssal socket",
        "org": [],
        "params": [
            {
                "pos": 0,
                "type": "R",
                "value": ""
            }
        ]
    },
    "minions have #% increased maximum life": {
        "gen": "minions have #% increased maximum life",
        "org": [],
        "params": [
            {
                "pos": 0,
                "type": "R",
                "value": ""
            }
        ]
    },
    "prefixes cannot be changed": {
        "gen": "prefixes cannot be changed",
        "org": "prefixes cannot be changed",
        "params": []
    },
    "reflects # physical damage to melee attackers": {
        "gen": "reflects # physical damage to melee attackers",
        "org": [],
        "params": [
            {
                "pos": 0,
                "type": "R",
                "value": ""
            }
        ]
    },
    "socketed attacks have # to total mana cost": {
        "gen": "socketed attacks have # to total mana cost",
        "org": [],
        "params": [
            {
                "pos": 0,
                "type": "R",
                "value": ""
            }
        ]
    },
    "socketed attacks have -# to total mana cost": {
        "gen": "socketed attacks have -# to total mana cost",
        "org": [],
        "params": [
            {
                "pos": 0,
                "type": "R",
                "value": ""
            }
        ]
    },
    "socketed gems are supported by level # fortify": {
        "gen": "socketed gems are supported by level # fortify",
        "org": [],
        "params": [
            {
                "pos": 0,
                "type": "R",
                "value": ""
            }
        ]
    },
    "socketed gems are supported by level # increased duration": {
        "gen": "socketed gems are supported by level # increased duration",
        "org": [],
        "params": [
            {
                "pos": 0,
                "type": "R",
                "value": ""
            }
        ]
    },
    "socketed gems are supported by level # life leech": {
        "gen": "socketed gems are supported by level # life leech",
        "org": [],
        "params": [
            {
                "pos": 0,
                "type": "R",
                "value": ""
            }
        ]
    },
    "socketed gems are supported by level # ranged attack totem": {
        "gen": "socketed gems are supported by level # ranged attack totem",
        "org": [],
        "params": [
            {
                "pos": 0,
                "type": "R",
                "value": ""
            }
        ]
    },
    "socketed gems are supported by level # spell totem": {
        "gen": "socketed gems are supported by level # spell totem",
        "org": [],
        "params": [
            {
                "pos": 0,
                "type": "R",
                "value": ""
            }
        ]
    },
    "socketed spells have #% reduced mana cost": {
        "gen": "socketed spells have #% reduced mana cost",
        "org": [],
        "params": [
            {
                "pos": 0,
                "type": "R",
                "value": ""
            }
        ]
    },
    "socketed spells have -#% reduced mana cost": {
        "gen": "socketed spells have -#% reduced mana cost",
        "org": [],
        "params": [
            {
                "pos": 0,
                "type": "R",
                "value": ""
            }
        ]
    },
    "suffixes cannot be changed": {
        "gen": "suffixes cannot be changed",
        "org": "suffixes cannot be changed",
        "params": []
    },
    "unaffected by burning ground": {
        "gen": "unaffected by burning ground",
        "org": "unaffected by burning ground",
        "params": []
    },
    "unaffected by chilled ground": {
        "gen": "unaffected by chilled ground",
        "org": "unaffected by chilled ground",
        "params": []
    },
    "unaffected by desecrated ground": {
        "gen": "unaffected by desecrated ground",
        "org": "unaffected by desecrated ground",
        "params": []
    },
    "unaffected by shocked ground": {
        "gen": "unaffected by shocked ground",
        "org": "unaffected by shocked ground",
        "params": []
    }
}